setup.cfg
setup.py
pyother/__init__.py
pyother/monitoring.py
pyother/script.py
pyother.egg-info/PKG-INFO
pyother.egg-info/SOURCES.txt
pyother.egg-info/dependency_links.txt
pyother.egg-info/top_level.txt