Metadata-Version: 1.1
Name: pyother
Version: 1.2.2
Summary: Some reusable code snippets
Home-page: https://github.com/vespian/pyother
Author: Vespian
Author-email: vespian a t wp.pl
License: ASF2.0
Download-URL: https://github.com/vespian/pyother/tarball/1.2.2
Keywords: locking,logging,utils
Platform: UNKNOWN
